betty_nginx/__init__.py
betty_nginx/_cli.py
betty_nginx/artifact.py
betty_nginx/config.py
betty_nginx/docker.py
betty_nginx/py.typed
betty_nginx/serve.py
betty_nginx/assets/Dockerfile
betty_nginx/assets/content_negotiation.lua
betty_nginx/assets/nginx.conf.j2
betty_nginx/assets/locale/betty.pot
betty_nginx-0.1.0.dist-info/LICENSE.txt
betty_nginx-0.1.0.dist-info/METADATA
betty_nginx-0.1.0.dist-info/WHEEL
betty_nginx-0.1.0.dist-info/entry_points.txt
betty_nginx-0.1.0.dist-info/top_level.txt
betty_nginx-0.1.0.dist-info/RECORD
