Metadata-Version: 2.1
Name: betty_nginx
Version: 0.1.0
Summary: Nginx for Betty provides nginx and Docker integration for your Betty sites
Author-email: Bart Feenstra <bar@bartfeenstra.com>
License: GNU GENERAL PUBLIC LICENSE
Project-URL: Github, https://github.com/bartfeenstra/betty-nginx
Project-URL: Twitter, https://twitter.com/BettyProject
Project-URL: X, https://twitter.com/BettyProject
Classifier: Environment :: Console
Classifier: Intended Audience :: Developers
Classifier: Intended Audience :: End Users/Desktop
Classifier: Intended Audience :: Science/Research
Classifier: License :: OSI Approved :: GNU General Public License v3 or later (GPLv3+)
Classifier: Programming Language :: Lua
Classifier: Programming Language :: Python :: 3.11
Classifier: Programming Language :: Python :: 3.12
Classifier: Programming Language :: Python :: 3.13
Classifier: Programming Language :: Unix Shell
Classifier: Operating System :: MacOS :: MacOS X
Classifier: Operating System :: POSIX :: Linux
Classifier: Operating System :: Microsoft :: Windows
Classifier: Topic :: Internet
Classifier: Topic :: Scientific/Engineering :: Visualization
Classifier: Topic :: Sociology :: Genealogy
Classifier: Topic :: Sociology :: History
Classifier: Topic :: Software Development :: Code Generators
Classifier: Natural Language :: Dutch
Classifier: Natural Language :: English
Classifier: Natural Language :: French
Classifier: Natural Language :: German
Classifier: Natural Language :: Ukrainian
Classifier: Typing :: Typed 
Requires-Python: ~=3.11
License-File: LICENSE.txt
Requires-Dist: betty~=0.4.0
Requires-Dist: docker~=7.1
Provides-Extra: setuptools
Requires-Dist: twine~=6.0; extra == "setuptools"
Requires-Dist: wheel~=0.43; extra == "setuptools"
Provides-Extra: test
Requires-Dist: basedmypy~=2.5; extra == "test"
Requires-Dist: coverage~=7.6; extra == "test"
Requires-Dist: html5lib~=1.1; extra == "test"
Requires-Dist: pytest~=8.3; extra == "test"
Requires-Dist: pytest-asyncio~=0.23; extra == "test"
Requires-Dist: pytest-mock~=3.14; extra == "test"
Requires-Dist: ruff~=0.8; extra == "test"
Requires-Dist: types-aiofiles~=24.1; extra == "test"
Requires-Dist: types-html5lib~=1.1; extra == "test"
Requires-Dist: types-requests~=2.32; extra == "test"
Requires-Dist: virtualenv~=20.26; extra == "test"
Requires-Dist: betty_nginx[setuptools]; extra == "test"
Provides-Extra: development
Requires-Dist: pytest-repeat~=0.9; extra == "development"
Requires-Dist: betty_nginx[test]; extra == "development"
Provides-Extra: ci
Requires-Dist: codecov~=2.1; extra == "ci"
Requires-Dist: betty_nginx[test]; extra == "ci"
